pyiqa/__init__.py
pyiqa/api_helpers.py
pyiqa/default_model_configs.py
pyiqa/test.py
pyiqa/train.py
pyiqa/train_nsplits.py
pyiqa/version.py
pyiqa/archs/__init__.py
pyiqa/archs/ahiq_arch.py
pyiqa/archs/arch_util.py
pyiqa/archs/brisque_arch.py
pyiqa/archs/ckdn_arch.py
pyiqa/archs/cnniqa_arch.py
pyiqa/archs/dbcnn_arch.py
pyiqa/archs/dists_arch.py
pyiqa/archs/fid_arch.py
pyiqa/archs/fsim_arch.py
pyiqa/archs/func_util.py
pyiqa/archs/gmsd_arch.py
pyiqa/archs/hypernet_arch.py
pyiqa/archs/inception.py
pyiqa/archs/iqt_arch.py
pyiqa/archs/lpips_arch.py
pyiqa/archs/mad_arch.py
pyiqa/archs/maniqa_arch.py
pyiqa/archs/maniqa_swin.py
pyiqa/archs/musiq_arch.py
pyiqa/archs/nima_arch.py
pyiqa/archs/niqe_arch.py
pyiqa/archs/nlpd_arch.py
pyiqa/archs/nrqm_arch.py
pyiqa/archs/paq2piq_arch.py
pyiqa/archs/pieapp_arch.py
pyiqa/archs/psnr_arch.py
pyiqa/archs/ssim_arch.py
pyiqa/archs/vif_arch.py
pyiqa/archs/vsi_arch.py
pyiqa/archs/wadiqam_arch.py
pyiqa/data/__init__.py
pyiqa/data/ava_dataset.py
pyiqa/data/bapps_dataset.py
pyiqa/data/data_sampler.py
pyiqa/data/data_util.py
pyiqa/data/flive_dataset.py
pyiqa/data/general_fr_dataset.py
pyiqa/data/general_nr_dataset.py
pyiqa/data/livechallenge_dataset.py
pyiqa/data/multiscale_trans_util.py
pyiqa/data/pieapp_dataset.py
pyiqa/data/pipal_dataset.py
pyiqa/data/prefetch_dataloader.py
pyiqa/data/transforms.py
pyiqa/losses/__init__.py
pyiqa/losses/iqa_losses.py
pyiqa/losses/loss_util.py
pyiqa/losses/losses.py
pyiqa/matlab_utils/__init__.py
pyiqa/matlab_utils/functions.py
pyiqa/matlab_utils/math_util.py
pyiqa/matlab_utils/resize.py
pyiqa/matlab_utils/scfpyr_util.py
pyiqa/metrics/__init__.py
pyiqa/metrics/correlation_coefficient.py
pyiqa/metrics/other_metrics.py
pyiqa/models/__init__.py
pyiqa/models/bapps_model.py
pyiqa/models/base_model.py
pyiqa/models/dbcnn_model.py
pyiqa/models/general_iqa_model.py
pyiqa/models/hypernet_model.py
pyiqa/models/inference_model.py
pyiqa/models/lr_scheduler.py
pyiqa/models/nima_model.py
pyiqa/models/pieapp_model.py
v_pyiqa-0.1.5.dist-info/LICENSE
v_pyiqa-0.1.5.dist-info/LICENSE_NTU-S-Lab
v_pyiqa-0.1.5.dist-info/METADATA
v_pyiqa-0.1.5.dist-info/WHEEL
v_pyiqa-0.1.5.dist-info/top_level.txt
v_pyiqa-0.1.5.dist-info/RECORD
