Metadata-Version: 2.1
Name: v-pyiqa
Version: 0.1.5
Summary: PyTorch Toolbox for Image Quality Assessment
Home-page: https://github.com/chaofengc/IQA-PyTorch
Author: Chaofeng Chen
Author-email: chaofenghust@gmail.com
License: UNKNOWN
Keywords: image quality assessment,pytorch
Platform: UNKNOWN
Classifier: Development Status :: 3 - Alpha
Classifier: Intended Audience :: Science/Research
Classifier: License :: OSI Approved :: Apache Software License
Classifier: Operating System :: OS Independent
Classifier: Programming Language :: Python :: 3.6
Classifier: Programming Language :: Python :: 3.7
Classifier: Programming Language :: Python :: 3.8
Classifier: Topic :: Scientific/Engineering
Classifier: Topic :: Scientific/Engineering :: Image Processing
Requires-Python: >=3.6
Requires-Dist: addict
Requires-Dist: future
Requires-Dist: numpy
Requires-Dist: opencv-python-headless
Requires-Dist: torch (>=1.9)
Requires-Dist: torchvision (>=0.9)
Requires-Dist: Pillow
Requires-Dist: pyyaml
Requires-Dist: requests
Requires-Dist: scipy
Requires-Dist: timm
Requires-Dist: tqdm
Requires-Dist: yapf
Requires-Dist: einops
Provides-Extra: train
Requires-Dist: lmdb ; extra == 'train'
Requires-Dist: pandas ; extra == 'train'
Requires-Dist: imgaug ; extra == 'train'
